README.md
setup.py
watchlog_ai_tracer/__init__.py
watchlog_ai_tracer/tracer.py
watchlog_ai_tracer.egg-info/PKG-INFO
watchlog_ai_tracer.egg-info/SOURCES.txt
watchlog_ai_tracer.egg-info/dependency_links.txt
watchlog_ai_tracer.egg-info/requires.txt
watchlog_ai_tracer.egg-info/top_level.txt