Metadata-Version: 2.1
Name: watchlog-ai-tracer
Version: 0.1.0
Summary: Lightweight Python tracer for Watchlog AI monitoring
Home-page: https://github.com/Watchlog-monitoring/python-ai-tracer
Author: Mohammadreza
Author-email: mohammadnajm75@gmail.com
License: MIT
Classifier: Development Status :: 4 - Beta
Classifier: Programming Language :: Python :: 3
Classifier: License :: OSI Approved :: MIT License
Classifier: Operating System :: OS Independent
Requires-Python: >=3.7
Requires-Dist: requests>=2.25.0
Requires-Dist: filelock>=3.0.0
Requires-Dist: dnspython>=2.0.0
